censor.py
censorbot-0.0.7.dist-info/METADATA
censorbot-0.0.7.dist-info/WHEEL
censorbot-0.0.7.dist-info/entry_points.txt
censorbot-0.0.7.dist-info/top_level.txt
censorbot-0.0.7.dist-info/RECORD
