Metadata-Version: 2.4
Name: censorbot
Version: 0.0.7
Summary: Automatically censor profanity in video files using AI transcription
Home-page: https://github.com/samuelmukoti/censorbot
Author: Samuel Mukoti
Author-email: Samuel Mukoti <contact@samuelmukoti.com>
License: GPL-3.0
Project-URL: Homepage, https://github.com/samuelmukoti/censorbot
Project-URL: Documentation, https://github.com/samuelmukoti/censorbot#readme
Project-URL: Repository, https://github.com/samuelmukoti/censorbot
Project-URL: Bug Reports, https://github.com/samuelmukoti/censorbot/issues
Keywords: video,censoring,profanity,subtitles,whisper,ai,transcription
Classifier: Development Status :: 4 - Beta
Classifier: Intended Audience :: End Users/Desktop
Classifier: Topic :: Multimedia :: Video
Classifier: License :: OSI Approved :: GNU General Public License v3 (GPLv3)
Classifier: Programming Language :: Python :: 3
Classifier: Programming Language :: Python :: 3.8
Classifier: Programming Language :: Python :: 3.9
Classifier: Programming Language :: Python :: 3.10
Classifier: Programming Language :: Python :: 3.11
Classifier: Programming Language :: Python :: 3.12
Requires-Python: >=3.8
Requires-Dist: torch>=2.0.0
Requires-Dist: faster-whisper>=1.0.0
Requires-Dist: numpy<2.0.0,>=1.24.0
Requires-Dist: pysrt>=1.1.2
Requires-Dist: subliminal==2.1.0
Requires-Dist: babelfish>=0.6.0
Requires-Dist: ffmpeg-python>=0.2.0
Requires-Dist: chardet>=5.0.0
Requires-Dist: tqdm>=4.65.0
Requires-Dist: requests>=2.31.0
Requires-Dist: guessit>=3.7.1
Requires-Dist: click>=8.0.0
Requires-Dist: pyyaml>=6.0.0
Requires-Dist: mlx>=0.4.0; platform_system == "Darwin" and platform_machine == "arm64"
Requires-Dist: mlx-whisper>=0.4.0; platform_system == "Darwin" and platform_machine == "arm64"
Provides-Extra: mlx
Requires-Dist: mlx>=0.4.0; extra == "mlx"
Requires-Dist: mlx-whisper>=0.4.0; extra == "mlx"
Provides-Extra: dev
Requires-Dist: pytest>=7.0.0; extra == "dev"
Requires-Dist: pytest-cov>=4.0.0; extra == "dev"
Requires-Dist: black>=23.0.0; extra == "dev"
Requires-Dist: flake8>=6.0.0; extra == "dev"
Requires-Dist: mypy>=1.0.0; extra == "dev"
Dynamic: author
Dynamic: home-page
Dynamic: requires-python
